sqlmodel_activerecord/__init__.py
sqlmodel_activerecord/mixin.py
sqlmodel_activerecord_mixin-0.1.0.dist-info/METADATA
sqlmodel_activerecord_mixin-0.1.0.dist-info/WHEEL
sqlmodel_activerecord_mixin-0.1.0.dist-info/top_level.txt
sqlmodel_activerecord_mixin-0.1.0.dist-info/RECORD
