Metadata-Version: 2.4
Name: sqlmodel-activerecord-mixin
Version: 0.1.0
Summary: Active Record-style convenience methods (Model.query, save, delete) for SQLModel with Flask-SQLAlchemy.
Author: SQLModel ActiveRecordMixin contributors
License-Expression: MIT
Project-URL: Repository, https://github.com/your-username/sqlmodel-activerecord-mixin
Project-URL: Documentation, https://github.com/your-username/sqlmodel-activerecord-mixin#readme
Keywords: sqlmodel,sqlalchemy,flask,activerecord,orm
Classifier: Development Status :: 4 - Beta
Classifier: Intended Audience :: Developers
Classifier: Programming Language :: Python :: 3
Classifier: Programming Language :: Python :: 3.9
Classifier: Programming Language :: Python :: 3.10
Classifier: Programming Language :: Python :: 3.11
Classifier: Programming Language :: Python :: 3.12
Classifier: Programming Language :: Python :: 3.13
Classifier: Topic :: Software Development :: Libraries :: Python Modules
Requires-Python: >=3.9
Requires-Dist: flask>=2.0
Requires-Dist: flask-sqlalchemy>=3.0
Requires-Dist: sqlmodel>=0.0.14
